paiohttpclient/__init__.py
paiohttpclient/http/__init__.py
paiohttpclient/http/graphql_response.py
paiohttpclient/http/http_client.py
paiohttpclient/http/http_error.py
paiohttpclient/utils/__init__.py
paiohttpclient/utils/jsonable_encoder.py
paiohttpclient-0.0.1.dist-info/METADATA
paiohttpclient-0.0.1.dist-info/WHEEL
paiohttpclient-0.0.1.dist-info/top_level.txt
paiohttpclient-0.0.1.dist-info/RECORD
