Metadata-Version: 2.1
Name: paiohttpclient
Version: 0.0.1
Summary: Easy to use python http client based on aiohttp and pydantic.
Home-page: UNKNOWN
Author: Pylakey
Author-email: pylakey@protonmail.com
License: MIT License
Platform: UNKNOWN
Classifier: Programming Language :: Python :: 3
Classifier: License :: OSI Approved :: MIT License
Classifier: Operating System :: OS Independent
Requires-Python: >=3.9
Requires-Dist: aiohttp[speedups] (>=3.7.4)
Requires-Dist: ujson (>=4.0.2)
Requires-Dist: pydantic (>=1.8.2)
Requires-Dist: tenacity (>=7.0.0)
Requires-Dist: graphql-core
